klustaviewa/__init__.py
klustaviewa/control/__init__.py
klustaviewa/control/controller.py
klustaviewa/control/processor.py
klustaviewa/control/stack.py
klustaviewa/control/tests/__init__.py
klustaviewa/control/tests/test_controller.py
klustaviewa/control/tests/test_processor.py
klustaviewa/control/tests/test_stack.py
klustaviewa/gui/__init__.py
klustaviewa/gui/buffer.py
klustaviewa/gui/dock.py
klustaviewa/gui/icons.py
klustaviewa/gui/kwikskope.py
klustaviewa/gui/mainwindow.py
klustaviewa/gui/rcicons.py
klustaviewa/gui/recluster.py
klustaviewa/gui/styles.css
klustaviewa/gui/taskgraph.py
klustaviewa/gui/threads.py
klustaviewa/gui/tests/__init__.py
klustaviewa/gui/tests/test_buffer.py
klustaviewa/gui/tests/test_mainwindow.py
klustaviewa/gui/tests/test_recluster.py
klustaviewa/gui/tests/test_taskgraph.py
klustaviewa/icons/checkbox.png
klustaviewa/icons/close.png
klustaviewa/icons/dock.png
klustaviewa/icons/dockable.png
klustaviewa/icons/down.png
klustaviewa/icons/down_arrow.png
klustaviewa/icons/favicon.ico
klustaviewa/icons/flip.png
klustaviewa/icons/fullscreen.png
klustaviewa/icons/hand.png
klustaviewa/icons/handle.png
klustaviewa/icons/home.png
klustaviewa/icons/logo.png
klustaviewa/icons/magic.png
klustaviewa/icons/merge.png
klustaviewa/icons/minimize.png
klustaviewa/icons/move.png
klustaviewa/icons/multiunit.png
klustaviewa/icons/noise.png
klustaviewa/icons/open.png
klustaviewa/icons/override_color.png
klustaviewa/icons/pin.png
klustaviewa/icons/probe.png
klustaviewa/icons/redo.png
klustaviewa/icons/save.png
klustaviewa/icons/saveas.png
klustaviewa/icons/search.png
klustaviewa/icons/selection.png
klustaviewa/icons/split.png
klustaviewa/icons/undo.png
klustaviewa/icons/up.png
klustaviewa/scripts/__init__.py
klustaviewa/scripts/runklustaviewa.py
klustaviewa/scripts/runkwikskope.py
klustaviewa/stats/__init__.py
klustaviewa/stats/cache.py
klustaviewa/stats/ccg.py
klustaviewa/stats/correlations.py
klustaviewa-0.4.7.dist-info/DESCRIPTION.rst
klustaviewa-0.4.7.dist-info/METADATA
klustaviewa-0.4.7.dist-info/RECORD
klustaviewa-0.4.7.dist-info/WHEEL
klustaviewa-0.4.7.dist-info/entry_points.txt
klustaviewa-0.4.7.dist-info/metadata.json
klustaviewa-0.4.7.dist-info/top_level.txt
