Metadata-Version: 2.0
Name: klustaviewa
Version: 0.4.7
Summary: Spike sorting software suite.
Home-page: https://klusta-team.github.io
Author: Cyrille Rossant
Author-email: rossant@github
License: LICENSE.md
Platform: UNKNOWN
